paranoid_model/__init__.py
paranoid_model/admin.py
paranoid_model/apps.py
paranoid_model/exceptions.py
paranoid_model/manager.py
paranoid_model/models.py
paranoid_model/queryset.py
paranoid_model/views.py
paranoid_model/migrations/__init__.py
paranoid_model/templates/admin/paranoid_model/change_form.html
paranoid_model/tests/__init__.py
paranoid_model/tests/models.py
paranoid_model/tests/test_one_to_one_field.py
paranoid_model/tests/test_related_model.py
paranoid_model/tests/test_settings.py
paranoid_model/tests/test_singles_model.py
django_paranoid_model-1.0.7.dist-info/LICENSE.md
django_paranoid_model-1.0.7.dist-info/METADATA
django_paranoid_model-1.0.7.dist-info/WHEEL
django_paranoid_model-1.0.7.dist-info/top_level.txt
django_paranoid_model-1.0.7.dist-info/RECORD
