Metadata-Version: 2.1
Name: django-paranoid-model
Version: 1.0.7
Summary: Django abstract model with paranoid behavior.
Home-page: https://github.com/DarknessRdg/django-paranoid-model
Author: Luan Rodrigues
Author-email: luanrodriguesbusiness@hotmail.com
License: UNKNOWN
Project-URL: Bug Reports, https://github.com/DarknessRdg/django-paranoid-model/issues
Project-URL: Source, https://github.com/DarknessRdg/django-paranoid-model/
Keywords: django paranoid safedelete softdelete
Platform: UNKNOWN
Classifier: Development Status :: 4 - Beta
Classifier: Intended Audience :: Developers
Classifier: Programming Language :: Python :: 3
Classifier: License :: OSI Approved :: MIT License
Classifier: Operating System :: OS Independent
Requires-Python: >=3.4
Requires-Dist: Django (>=1.11.0)
Provides-Extra: test
Requires-Dist: Faker (==5.0.1) ; extra == 'test'
Requires-Dist: model-bakery (==1.2.0) ; extra == 'test'
Requires-Dist: ipdb (==0.10.1) ; extra == 'test'
Requires-Dist: pytest (==6.2.1) ; extra == 'test'
Requires-Dist: pytest-django (==4.1.0) ; extra == 'test'
Requires-Dist: pytest-cov (==2.11.1) ; extra == 'test'
Requires-Dist: tox (==3.21.2) ; extra == 'test'
